colab_vscode_bridge/__init__.py
colab_vscode_bridge/auth.py
colab_vscode_bridge/colab_upload.py
colab_vscode_bridge/download.py
colab_vscode_bridge/kaggle_upload.py
colab_vscode_bridge/utils.py
colab_vscode_bridge-0.1.4.dist-info/licenses/LICENSE
colab_vscode_bridge-0.1.4.dist-info/METADATA
colab_vscode_bridge-0.1.4.dist-info/WHEEL
colab_vscode_bridge-0.1.4.dist-info/RECORD
