Metadata-Version: 2.4
Name: colab-vscode-bridge
Version: 0.1.4
Summary: A utility package that fills functionality gaps in the Colab extension for VS Code. It provides helper functions for tasks not natively supported, including simplified Kaggle authentication, direct file uploads from Colab to Kaggle, and downloading small files from a Colab runtime to the local VS Code environment.
License-Expression: MIT
License-File: LICENSE
Keywords: colab,kaggle,jupyter,upload,download
Author: ranidzkellou
Author-email: kellour77@gmail.com
Requires-Python: >=3.12
Classifier: Programming Language :: Python :: 3
Classifier: Programming Language :: Python :: 3.12
Classifier: Programming Language :: Python :: 3.13
Classifier: Programming Language :: Python :: 3.14
Requires-Dist: ipython (>=8.0.0)
Requires-Dist: ipywidgets (>=8.0.0)
Requires-Dist: kaggle (>=1.5.0)
